[
    {
        "NO.": 1,
        "제목": "반품해주세요.",
        "내용": "사이즈가 안맞아서 반품요청",
        "작성자": "김예슬",
        "작성일자": "2019-08-09",
        "수정자": "김예슬",
        "수정일자": "2019-08-10"
    },
    {
        "NO.": 2,
        "제목": "교환.",
        "내용": "교환요청",
        "작성자": "강다니엘",
        "작성일자": "2019-08-09",
        "수정자": "강다니엘",
        "수정일자": "2019-08-10"
    },
    {
        "NO.": 3,
        "제목": "상품이 안와요.",
        "내용": "배송지연",
        "작성자": "박보검",
        "작성일자": "2019-08-09",
        "수정자": "박보검",
        "수정일자": "2019-08-10"
    }
]